ref2tex/__init__.py
ref2tex/apa2tex.py
ref2tex/ieee2tex.py
ref2tex-0.0.2.dist-info/LICENSE
ref2tex-0.0.2.dist-info/METADATA
ref2tex-0.0.2.dist-info/WHEEL
ref2tex-0.0.2.dist-info/top_level.txt
ref2tex-0.0.2.dist-info/RECORD
