Metadata-Version: 2.1
Name: ref2tex
Version: 0.0.2
Summary: A package that converts inline citation (i.e. (Sahraoui et al. 2023), or [1]) to latex cite command: \cite(bibkeyname)
Author-email: Sahraoui Dhelim <sahraoui.dhelim@hotmail.com>
License: MIT License
Project-URL: repository, https://github.com/sahraoui17
Project-URL: homepage, https://github.com/sahraoui17
Keywords: references,biblography,latex,citation,bib
Requires-Python: >=3.7
License-File: LICENSE
Requires-Dist: bibtexparser
